Metadata-Version: 2.4
Name: paylix-python-sdk
Version: 1.0.9.1
Home-page: https://github.com/Paylix/python-sdk
License-File: LICENSE
Requires-Dist: requests
Dynamic: description
Dynamic: description-content-type
Dynamic: home-page
Dynamic: license-file
Dynamic: requires-dist
